qtmaterialsymbols/__init__.py
qtmaterialsymbols/browser.py
qtmaterialsymbols/exceptions.py
qtmaterialsymbols/iconic_font.py
qtmaterialsymbols/structures.py
qtmaterialsymbols/utils.py
qtmaterialsymbols/version.py
qtmaterialsymbols/resources/MaterialSymbolsOutlined.codepoints
qtmaterialsymbols/resources/MaterialSymbolsOutlined.json
qtmaterialsymbols/resources/MaterialSymbolsOutlined.ttf
qtmaterialsymbols/resources/__init__.py
qtmaterialsymbols-1.0.1.dist-info/licenses/LICENSE
qtmaterialsymbols-1.0.1.dist-info/METADATA
qtmaterialsymbols-1.0.1.dist-info/WHEEL
qtmaterialsymbols-1.0.1.dist-info/top_level.txt
qtmaterialsymbols-1.0.1.dist-info/RECORD
