Metadata-Version: 2.4
Name: qtmaterialsymbols
Version: 1.0.1
Summary: Material Symbols in PySide and PyQt applications
Author-email: Jakub Trllo <jakub.trllo@gmail.com>
License-Expression: MIT
Project-URL: Repository, https://github.com/iLLiCiTiT/qtmaterialsymbols
Project-URL: Issues, https://github.com/iLLiCiTiT/qtmaterialsymbols/issues
Keywords: PySide,PyQt,Qt,Material Symbols,Icons
Requires-Python: >=3.7
License-File: LICENSE
Requires-Dist: qtpy
Dynamic: license-file
